guia_1/ejercicio1/ejercicio1.v
//Diseñe un módulo en Verilog que implemente un sumador completo de un bit con entradas a,b y
//cin(carry in), y salidas sum y cout (carry out). Describir y simular con Icarus Verilog + GTKWave.

module fulladder (
    input wire a, b, cin,
    output wire s, cout
);

assign s = a ^ b ^ cin;
assign cout = (a & b) | cin & (a ^ b);

endmodule

guia_1/ejercicio1/ejercicio1_tb.v
`timescale 1ns/1ps
`include "ejercicio1.v"

module ejercicio1_tb;
    reg a,b,cin;
    wire s, cout;

    
    fulladder uud(
        .a(a),
        .b(b),
        .cin(cin),
        .s(s),
        .cout(cout)
    );

    initial begin
        $dumpfile("ejercicio1.vcd");
        $dumpvars(0, ejercicio1_tb);
        $monitor("At time %0t: a=%b, b=%b, cin=%b -> sum=%b, carry=%b", $time, a, b, cin, s, cout);


        //every variable value combination
        a=0; b=0; cin=0; #10;
        a=0; b=0; cin=1; #10;
        a=0; b=1; cin=0; #10;
        a=0; b=1; cin=1; #10;
        a=1; b=0; cin=0; #10;
        a=1; b=0; cin=1; #10;
        a=1; b=1; cin=0; #10;
        a=1; b=1; cin=1; #10;

        $finish;
    end
endmodule

guia_1/ejercicio1/ejercicio1.vcd
$date
	Fri Aug 14 13:34:09 2026
$end
$version
	Icarus Verilog
$end
$timescale
	1ps
$end
$scope module ejercicio1_tb $end
$var wire 1 ! s $end
$var wire 1 " cout $end
$var reg 1 # a $end
$var reg 1 $ b $end
$var reg 1 % cin $end
$scope module uud $end
$var wire 1 # a $end
$var wire 1 $ b $end
$var wire 1 % cin $end
$var wire 1 " cout $end
$var wire 1 ! s $end
$upscope $end
$upscope $end
$enddefinitions $end
$comment Show the parameter values. $end
$dumpall
$end
#0
$dumpvars
0%
0$
0#
0"
0!
$end
#10000
1!
1%
#20000
0%
1$
#30000
1"
0!
1%
#40000
0"
1!
0%
0$
1#
#50000
1"
0!
1%
#60000
0%
1$
#70000
1!
1%
